napari_ctc_io/__init__.py
napari_ctc_io/_reader.py
napari_ctc_io/_version.py
napari_ctc_io/_writer.py
napari_ctc_io/napari.yaml
napari_ctc_io/reader.py
napari_ctc_io/_tests/__init__.py
napari_ctc_io/_tests/test_reader.py
napari_ctc_io/_tests/test_writer.py
napari_ctc_io/_tests/resources/edge_cases/TRA/000.tif
napari_ctc_io/_tests/resources/edge_cases/TRA/001.tif
napari_ctc_io/_tests/resources/edge_cases/TRA/002.tif
napari_ctc_io/_tests/resources/edge_cases/TRA/tracks.txt
napari_ctc_io/_tests/resources/fluo_simulated/TRA/README.md
napari_ctc_io/_tests/resources/fluo_simulated/TRA/man_track.txt
napari_ctc_io/_tests/resources/fluo_simulated/TRA/man_track000.tif
napari_ctc_io/_tests/resources/fluo_simulated/TRA/man_track001.tif
napari_ctc_io/_tests/resources/fluo_simulated/TRA/man_track002.tif
napari_ctc_io/_tests/resources/fluo_simulated/TRA/man_track003.tif
napari_ctc_io/_tests/resources/fluo_simulated/TRA/man_track004.tif
napari_ctc_io/_tests/resources/fluo_simulated/TRA/man_track005.tif
napari_ctc_io/_tests/resources/fluo_simulated/TRA/man_track006.tif
napari_ctc_io/_tests/resources/fluo_simulated/TRA/man_track007.tif
napari_ctc_io/_tests/resources/fluo_simulated/TRA/man_track008.tif
napari_ctc_io/_tests/resources/fluo_simulated/TRA/man_track009.tif
napari_ctc_io/_tests/resources/fluo_simulated/TRA/man_track010.tif
napari_ctc_io/_tests/resources/fluo_simulated/TRA/man_track011.tif
napari_ctc_io/_tests/resources/fluo_simulated/TRA/man_track012.tif
napari_ctc_io/_tests/resources/fluo_simulated/TRA/man_track013.tif
napari_ctc_io/_tests/resources/fluo_simulated/TRA/man_track014.tif
napari_ctc_io/_tests/resources/fluo_simulated/TRA/man_track015.tif
napari_ctc_io/_tests/resources/fluo_simulated/TRA/man_track016.tif
napari_ctc_io/_tests/resources/fluo_simulated/TRA/man_track017.tif
napari_ctc_io/_tests/resources/fluo_simulated/TRA/man_track018.tif
napari_ctc_io/_tests/resources/fluo_simulated/TRA/man_track019.tif
napari_ctc_io-0.2.1.dist-info/LICENSE
napari_ctc_io-0.2.1.dist-info/METADATA
napari_ctc_io-0.2.1.dist-info/WHEEL
napari_ctc_io-0.2.1.dist-info/entry_points.txt
napari_ctc_io-0.2.1.dist-info/top_level.txt
napari_ctc_io-0.2.1.dist-info/RECORD
