Metadata-Version: 2.1
Name: napari-ctc-io
Version: 0.2.1
Summary: Drag and drop/write tracks from/to the Cell Tracking Challenge (CTC) format.
Home-page: https://github.com/bentaculum/napari-ctc-io
Author: Benjamin Gallusser
Author-email: benjamin.gallusser@epfl.ch
License: BSD-3-Clause
Project-URL: Bug Tracker, https://github.com/bentaculum/napari-ctc-io/issues
Project-URL: Documentation, https://github.com/bentaculum/napari-ctc-io#README.md
Project-URL: Source Code, https://github.com/bentaculum/napari-ctc-io
Project-URL: User Support, https://github.com/bentaculum/napari-ctc-io/issues
Classifier: Development Status :: 3 - Alpha
Classifier: Framework :: napari
Classifier: License :: OSI Approved :: BSD License
Classifier: Operating System :: OS Independent
Classifier: Programming Language :: Python
Classifier: Programming Language :: Python :: 3
Classifier: Programming Language :: Python :: 3 :: Only
Classifier: Programming Language :: Python :: 3.9
Classifier: Programming Language :: Python :: 3.10
Classifier: Programming Language :: Python :: 3.11
Classifier: Topic :: Scientific/Engineering :: Image Processing
Requires-Python: >=3.9
License-File: LICENSE
Requires-Dist: napari
Requires-Dist: numpy
Requires-Dist: scikit-image
Requires-Dist: tifffile
Requires-Dist: pandas
Requires-Dist: imagecodecs
Provides-Extra: testing
Requires-Dist: tox; extra == "testing"
Requires-Dist: pytest; extra == "testing"
Requires-Dist: pytest-cov; extra == "testing"
